[
    {
        "id": 1,
        "title": "Tide (Feat. Ke'nekt)",
        "author": "Foria",
        "links": {
            "soundcloud": "https://soundcloud.com/foria/foria-tide-feat-kenekt",
            "ncm": "https://music.163.com/#/song?id=39443010"
        },
        "embed": {
            "soundcloud": 237174647,
            "ncm": 39443010
        }
    },
    {
        "id": 2,
        "title": "The Here, The Now",
        "author": "Casilofi",
        "links": {
            "soundcloud": "https://soundcloud.com/bitbirdofficial/casilofi-the-here-the-now",
            "ncm": "https://music.163.com/#/song?id=1333526305"
        },
        "embed": {
            "soundcloud": 551007315,
            "ncm": 1333526305
        }
    },
    {
        "id": 3,
        "title": "Get Up",
        "author": "RetroVision",
        "links": {
            "soundcloud": "https://soundcloud.com/hexagon/retrovision-get-up",
            "ncm": "https://music.163.com/#/song?id=1323458971"
        },
        "embed": {
            "soundcloud": 527194302,
            "ncm": 1323458971
        }
    },
    {
        "id": 4,
        "title": "Moe Anime OP Thing (Season 2)",
        "author": "Xeuphoria",
        "links": {
            "soundcloud": "https://soundcloud.com/xeuphoric/moe-anime-op-thing-season-2"
        },
        "embed": {
            "soundcloud": 482246637
        }
    },
    {
        "id": 5,
        "title": "STYX HELIX",
        "author": "Myth&Roid",
        "links": {
            "soundcloud": "https://soundcloud.com/yuuga_jailani/styx-helix-mythroid-rezero-kara-hajimeru-isekai-seikatsu-ed-full",
            "ncm": "https://music.163.com/#/song?id=413961906",
            "youtube": "https://www.youtube.com/watch?v=tIhL2KHVdgE"
        },
        "embed": {
            "soundcloud": 261771017,
            "ncm": 413961906,
            "youtube": "tIhL2KHVdgE"
        }
    },
    {
        "id": 6,
        "title": "VOXおるやんけ (ft.白上フブキ)",
        "author": "にーえぬこーは",
        "links": {
            "soundcloud": "https://soundcloud.com/yuuga_jailani/styx-helix-mythroid-rezero-kara-hajimeru-isekai-seikatsu-ed-full",
        },
        "embed": {
            "soundcloud": 499245867
        }
    }
]
